limepress/__init__.py
limepress/build_environment.py
limepress/command_line.py
limepress/context.py
limepress/default_settings.py
limepress/dependency_manager.py
limepress/file_system.py
limepress/parsing.py
limepress/plugin_manager.py
limepress/settings.py
limepress/templating.py
limepress/unit.py
limepress/plugins/__init__.py
limepress/plugins/html_parser.py
limepress/server/views/__init__.py
limepress/server/views/limepress_console.py
limepress/server/views/limepress_serve.py
limepress/templates/page.html
limepress/templates/snippets/pre.html
limepress-0.3.data/scripts/limepress
limepress-0.3.data/scripts/limepress-build
limepress-0.3.data/scripts/limepress-dev-server
limepress-0.3.data/scripts/limepress-shell
limepress-0.3.dist-info/LICENSE.txt
limepress-0.3.dist-info/METADATA
limepress-0.3.dist-info/WHEEL
limepress-0.3.dist-info/top_level.txt
limepress-0.3.dist-info/RECORD
