Metadata-Version: 2.1
Name: limepress
Version: 0.3
Summary: LimePress
Author-email: Florian Scherf <mail@florianscherf.de>
License: MIT License
Project-URL: Homepage, https://github.com/limepress/limepress
Project-URL: Repository, https://github.com/limepress/limepress
Project-URL: Bug Tracker, https://github.com/limepress/limepress/issues
Classifier: Development Status :: 4 - Beta
Classifier: Intended Audience :: Developers
Classifier: License :: OSI Approved :: MIT License
Classifier: Natural Language :: English
Classifier: Programming Language :: Python
Classifier: Programming Language :: Python :: 3
Classifier: Programming Language :: Python :: 3 :: Only
Classifier: Topic :: Software Development :: Libraries
Classifier: Topic :: System :: Software Distribution
Classifier: Environment :: Web Environment
Requires-Python: >=3.7
License-File: LICENSE.txt
Requires-Dist: simple-logging-setup
Requires-Dist: simple-plugin-manager
Requires-Dist: rlpython
Requires-Dist: jinja2 (>=2.10)
Requires-Dist: jinja2-simple-tags (==0.4.0)
Requires-Dist: beautifulsoup4
Requires-Dist: pyyaml (~=6.0)
Provides-Extra: packaging
Requires-Dist: build ; extra == 'packaging'
Requires-Dist: twine ; extra == 'packaging'
